setup.py
helloworldedge.egg-info/PKG-INFO
helloworldedge.egg-info/SOURCES.txt
helloworldedge.egg-info/dependency_links.txt
helloworldedge.egg-info/top_level.txt
src/__init__.py
src/hello_utils.py