Metadata-Version: 1.0
Name: helloworldedge
Version: 0.0.2
Summary: helloworldedge
Home-page: UNKNOWN
Author: Happy Puppy
Author-email: UNKNOWN
License: UNKNOWN
Platform: UNKNOWN
